readgroup_platform_insertion/__init__.py
readgroup_platform_insertion/__main__.py
readgroup_platform_insertion/main.py
readgroup_platform_insertion-0.19.dist-info/DESCRIPTION.rst
readgroup_platform_insertion-0.19.dist-info/METADATA
readgroup_platform_insertion-0.19.dist-info/RECORD
readgroup_platform_insertion-0.19.dist-info/WHEEL
readgroup_platform_insertion-0.19.dist-info/metadata.json
readgroup_platform_insertion-0.19.dist-info/top_level.txt
