Metadata-Version: 2.0
Name: readgroup-platform-insertion
Version: 0.19
Summary: Insert a PL:<value> in @RGs in a BAM header
Home-page: git@github.com:jeremiahsavage/readgroup_platform_insertion.git
Author: Jeremiah H. Savage
Author-email: jeremiahsavage@gmail.com
License: Apache 2.0
Platform: UNKNOWN
Classifier: Development Status :: 3 - Alpha
Classifier: Intended Audience :: Developers
Classifier: License :: OSI Approved :: Apache Software License
Classifier: Programming Language :: Python
Classifier: Programming Language :: Python :: 2
Classifier: Programming Language :: Python :: 3
Requires-Dist: cdis-pipe-utils
Requires-Dist: pandas
Requires-Dist: sqlalchemy
